{"trial_id": "2", "hyperparameters": {"space": [{"class_name": "Int", "config": {"name": "num_layers", "default": null, "conditions": [], "min_value": 1, "max_value": 10, "step": 1, "sampling": "linear"}}, {"class_name": "Int", "config": {"name": "units0", "default": null, "conditions": [], "min_value": 8, "max_value": 128, "step": 8, "sampling": "linear"}}, {"class_name": "Choice", "config": {"name": "activation0", "default": "relu", "conditions": [], "values": ["relu", "tanh", "sigmoid"], "ordered": false}}, {"class_name": "Choice", "config": {"name": "Dropout0", "default": 0.1, "conditions": [], "values": [0.1, 0.2, 0.3, 0.4, 0.5, 0.6, 0.7, 0.8, 0.9], "ordered": true}}, {"class_name": "Choice", "config": {"name": "optimizer", "default": "adam", "conditions": [], "values": ["adam", "sgd", "rmsprop", "adadelta", "nadam"], "ordered": false}}], "values": {"num_layers": 2, "units0": 32, "activation0": "sigmoid", "Dropout0": 0.5, "optimizer": "rmsprop"}}, "metrics": {"metrics": {"loss": {"direction": "min", "observations": [{"value": [0.7097852826118469], "step": 2}]}, "accuracy": {"direction": "max", "observations": [{"value": [0.5439739227294922], "step": 2}]}, "val_loss": {"direction": "min", "observations": [{"value": [0.6220746636390686], "step": 2}]}, "val_accuracy": {"direction": "max", "observations": [{"value": [0.7402597665786743], "step": 2}]}}}, "score": 0.7402597665786743, "best_step": 2, "status": "COMPLETED", "message": null}